response_measurer/__init__.py
response_measurer/calculaters.py
response_measurer/get.py
response_measurer/methods.py
response_measurer/post.py
response_measurer/print_out.py
response_measurer/run.py
response_measurer/tests/__init__.py
response_measurer-0.4.1.dist-info/entry_points.txt
response_measurer-0.4.1.dist-info/LICENSE
response_measurer-0.4.1.dist-info/WHEEL
response_measurer-0.4.1.dist-info/METADATA
response_measurer-0.4.1.dist-info/RECORD
